src/slpySign/slpySign.py
slpysign-0.0.0.dist-info/METADATA
slpysign-0.0.0.dist-info/WHEEL
slpysign-0.0.0.dist-info/licenses/LICENSE
slpysign-0.0.0.dist-info/RECORD
