Metadata-Version: 2.1
Name: slpySign
Version: 0.0.0
Summary: A slpySign emote generator!
Project-URL: Documentation, http://slpysign.rtfd.io/
Project-URL: Homepage, https://github.com/Pigeon43/slpySign
Project-URL: Issues / Bugs, https://github.com/Pigeon43/slpySign/issues
Project-URL: PyPI, https://pypi.org/project/slpysign/
Project-URL: Support Server, https://discord.gg/MyPTZBH4Q8
Author-email: thatgaypigeon <rapidpigeon43@gmail.com>
License: The MIT License (MIT)
License-File: LICENSE
Keywords: cute,emote,gaming,image,text,twitch,twitch.tv,uwu
Classifier: Development Status :: 5 - Production/Stable
Classifier: Intended Audience :: Developers
Classifier: License :: OSI Approved
Classifier: License :: OSI Approved :: MIT License
Classifier: Natural Language :: English
Classifier: Operating System :: OS Independent
Classifier: Programming Language :: Python
Classifier: Programming Language :: Python :: 3.8
Classifier: Programming Language :: Python :: 3.9
Classifier: Programming Language :: Python :: 3.10
Classifier: Programming Language :: Python :: 3.11
Classifier: Topic :: Games/Entertainment
Classifier: Topic :: Multimedia
Classifier: Topic :: Multimedia :: Graphics
Classifier: Topic :: Multimedia :: Graphics :: Editors
Classifier: Topic :: Multimedia :: Graphics :: Editors :: Raster-Based
Classifier: Topic :: Other/Nonlisted Topic
Classifier: Topic :: Software Development
Classifier: Topic :: Software Development :: Libraries
Classifier: Topic :: Software Development :: Libraries :: Python Modules
Classifier: Typing :: Typed
Requires-Python: >=3.8
